jakesutils/config.py
jakesutils/database.py
jakesutils/discord.py
jakesutils/download.py
jakesutils-0.4.dist-info/LICENSE
jakesutils-0.4.dist-info/METADATA
jakesutils-0.4.dist-info/WHEEL
jakesutils-0.4.dist-info/top_level.txt
jakesutils-0.4.dist-info/RECORD
