Metadata-Version: 2.1
Name: jakesutils
Version: 0.4
Summary: A collection of utils that I use all the time in my projects
Home-page: https://github.com/JakeRoggenbuck/jakesutils
Author: Jake Roggenbuck
Author-email: jake@jr0.org
License: MIT
Platform: UNKNOWN
Requires-Dist: PyYAML (>=5.4)
Requires-Dist: motor (==2.3.0)
Requires-Dist: pymongo (==3.11.0)
Requires-Dist: requests (==2.24.0)
Requires-Dist: tqdm (==4.50.1)
Requires-Dist: typeschemalib (==1.7)
